pytsg/__init__.py
pytsg/feature.py
pytsg/parse_tsg.py
pytsg-0.5.0.dist-info/licenses/LICENSE
pytsg-0.5.0.dist-info/METADATA
pytsg-0.5.0.dist-info/WHEEL
pytsg-0.5.0.dist-info/top_level.txt
pytsg-0.5.0.dist-info/RECORD
