Metadata-Version: 2.4
Name: pytsg
Version: 0.5.0
Summary: Library to read .tsg file package
License-Expression: MIT
License-File: LICENSE
Requires-Dist: numpy>1.23
Requires-Dist: pandas>1.4.3
Requires-Dist: simplejpeg>1.6.5
Requires-Dist: scipy>1.11.4
Requires-Dist: dhcomp
Provides-Extra: dev
Requires-Dist: black; extra == "dev"
Requires-Dist: Sphinx>5.1.1; extra == "dev"
Requires-Dist: sphinx-rtd-theme>1.0.0; extra == "dev"
Requires-Dist: sphinx-gallery>0.11.0; extra == "dev"
Requires-Dist: myst-parser>0.18.0; extra == "dev"
Requires-Dist: sphinx-autodoc-typehints>1.19.1; extra == "dev"
Requires-Dist: matplotlib>3.5.2; extra == "dev"
Provides-Extra: bigfile
Requires-Dist: zarr>2.16.1; extra == "bigfile"
Dynamic: license-file
